[
    {
        "title": "Apple Introduces What It Calls an Easier to Use Portable Music Player (2001)",
        "link": "http://www.nytimes.com/2001/10/24/business/technology-apple-introduces-what-it-calls-an-easier-to-use-portable-music-player.html"
    },
    {
        "title": "Tesla plunges in Consumer Reports' rankings",
        "link": "http://www.latimes.com/business/autos/la-fi-hy-tesla-consumer-reports-20161024-snap-story.html"
    },
    {
        "title": "IPFS-Screenshot – Like Cloudapp but with IPFS",
        "link": "https://github.com/uptownhr/ipfs-screenshot"
    },
    {
        "title": "Introducing Initialized Capital",
        "link": "http://initialized.com/"
    },
    {
        "title": "The “432 Hz vs. 440 Hz” conspiracy theory",
        "link": "https://jakubmarian.com/the-432-hz-vs-440-hz-conspiracy-theory"
    },
    {
        "title": "Ask HN: What is your favorite internet rabbit hole?",
        "link": "item?id=12778836"
    },
    {
        "title": "One Doom fan, 300 hours, and one gargantuan level",
        "link": "https://killscreen.com/articles/doom-map-300-hours-make/"
    },
    {
        "title": "A Taste of Haskell",
        "link": "https://hookrace.net/blog/a-taste-of-haskell/"
    },
    {
        "title": "We Got Phished",
        "link": "https://www.exploratorium.edu/blogs/tangents/we-got-phished-2"
    },
    {
        "title": "To influence people don't try to persuade them, use ‘pre-suasion’ instead",
        "link": "http://www.latimes.com/opinion/op-ed/la-oe-cialdini-presuasion-20161023-snap-story.html"
    },
    {
        "title": "Poor kids who do things right don't do better than rich kids who do things wrong",
        "link": "https://www.washingtonpost.com/news/wonk/wp/2014/10/18/poor-kids-who-do-everything-right-dont-do-better-than-rich-kids-who-do-everything-wrong/"
    },
    {
        "title": "Show HN: A Simple Highway Simulator",
        "link": "http://muehlemann.com/highwaysim"
    },
    {
        "title": "How many genes does it take to make a person?",
        "link": "https://theconversation.com/how-many-genes-does-it-take-to-make-a-person-64284?utm_medium=email&utm_campaign=Latest%20from%20The%20Conversation%20for%20October%2021%202016&utm_content=Latest%20from%20The%20Conversation%20for%20October%2021%202016+CID_171026d4d60e023d8e933b20d398a1a8&utm_source=campaign_monitor_us&utm_term=How%20many%20genes%20does%20it%20take%20to%20make%20a%20person"
    },
    {
        "title": "A Book by Its Cover: The strange history of books bound in human skin",
        "link": "http://laphamsquarterly.org/roundtable/book-its-cover"
    },
    {
        "title": "Can you hurt yourself eating chilli peppers?",
        "link": "http://www.bbc.com/future/story/20161020-can-you-hurt-yourself-eating-chilli-peppers"
    },
    {
        "title": "Font Awesome 5",
        "link": "http://five.fontawesome.io"
    },
    {
        "title": "Sputtering Startups Weigh on U.S. Economic Growth",
        "link": "http://www.wsj.com/articles/sputtering-startups-weigh-on-u-s-economic-growth-1477235874"
    },
    {
        "title": "Webcams used to attack Reddit and Twitter recalled",
        "link": "http://www.bbc.com/news/technology-37750798"
    },
    {
        "title": "Overview of JavaScript ES6 features",
        "link": "http://adrianmejia.com/blog/2016/10/19/Overview-of-JavaScript-ES6-features-a-k-a-ECMAScript-6-and-ES2015/#.WA4G-3dZebs.hackernews"
    },
    {
        "title": "Welcoming Adrian Cockcroft to the AWS Team",
        "link": "http://www.allthingsdistributed.com/2016/10/welcoming-adrian-cockcroft-to-tthe-aws-team.html"
    },
    {
        "title": "Building your bot's brain with Node.js and spaCy",
        "link": "https://explosion.ai/blog/chatbot-node-js-spacy"
    },
    {
        "title": "What it means when a huge Antarctic glacier is unstable",
        "link": "https://www.washingtonpost.com/news/energy-environment/wp/2016/10/21/scientists-just-showed-what-it-truly-means-when-a-huge-antarctic-glacier-is-unstable/?utm_term=.3c2b1868f451"
    },
    {
        "title": "What Libraries Can (Still) Do (2015)",
        "link": "http://www.nybooks.com/daily/2015/10/26/what-libraries-can-still-do-bibliotech/"
    },
    {
        "title": "Show HN: Automatic tool to summarize any text, document, or URL",
        "link": "http://summarizer.intellexer.com/"
    },
    {
        "title": "The world’s knowledge is being buried in a salt mine",
        "link": "http://www.bbc.com/future/story/20161018-the-worlds-knowledge-is-being-buried-in-a-salt-mine"
    },
    {
        "title": "Intrinsic: An Open-Source, Cross-Platform Vulkan Game Engine",
        "link": "http://www.intrinsic-engine.com/intrinsic-available/"
    },
    {
        "title": "How Snowden's Disclosures Made All Our Data Safer",
        "link": "https://pardonsnowden.org/news/snowden-effect-on-tech"
    },
    {
        "title": "Smartwatch sales are tanking",
        "link": "https://techcrunch.com/2016/10/24/smartwatch-sales-are-tanking/?ncid=rss"
    },
    {
        "title": "OpenSSL SSL3_AL_WARNING undefined alert remote DoS",
        "link": "http://seclists.org/oss-sec/2016/q4/224"
    }
]